pmgweb/__init__.py
pmgweb-0.0.2.dist-info/METADATA
pmgweb-0.0.2.dist-info/WHEEL
pmgweb-0.0.2.dist-info/top_level.txt
pmgweb-0.0.2.dist-info/RECORD
