Metadata-Version: 2.1
Name: pmgweb
Version: 0.0.2
Summary: PMG+ Web and Web Service Tools
Author-email: Preston Meyer Group <dev@pmgroup.ch>
License: MIT
Keywords: tools,utils
Classifier: Development Status :: 4 - Beta
Classifier: Programming Language :: Python :: 3
Classifier: Operating System :: OS Independent
Classifier: Intended Audience :: Developers
Classifier: License :: OSI Approved :: MIT License
Requires-Python: >=3.9
Provides-Extra: test
Requires-Dist: pytest ; extra == 'test'
Requires-Dist: hypothesis ; extra == 'test'
